chora_mcp_orchestration/__init__.py
chora_mcp_orchestration/cli.py
chora_mcp_orchestration/mcp_stdio.py
chora_mcp_orchestration/orchestrator.py
chora_mcp_orchestration/server.py
chora_mcp_orchestration-0.2.1.dist-info/entry_points.txt
chora_mcp_orchestration-0.2.1.dist-info/METADATA
chora_mcp_orchestration-0.2.1.dist-info/WHEEL
chora_mcp_orchestration-0.2.1.dist-info/RECORD
